dyplot/bar.py
dyplot/c3.py
dyplot/dygraphs.py
dyplot/hist.py
dyplot/nvd3.py
dyplot/pie.py
dyplot/scatter.py
dyplot/__init__.py
dyplot-0.8.8.dist-info/DESCRIPTION.rst
dyplot-0.8.8.dist-info/METADATA
dyplot-0.8.8.dist-info/metadata.json
dyplot-0.8.8.dist-info/RECORD
dyplot-0.8.8.dist-info/top_level.txt
dyplot-0.8.8.dist-info/WHEEL
