Metadata-Version: 2.0
Name: dyplot
Version: 0.8.8
Summary: matplotlib-like plot functions for dygraphs.js and c3.js.
Home-page: https://dyplot.readthedocs.org
Author: Tsung-Han Yang
Author-email: blacksburg98@yahoo.com
License: LICENSE.txt
Platform: UNKNOWN
Classifier: Topic :: Text Processing :: Markup :: HTML
Classifier: Topic :: Software Development :: Code Generators
Classifier: Topic :: Scientific/Engineering :: Visualization
Classifier: Programming Language :: JavaScript
Requires-Dist: pandas (>=0.7.3)
